gsheetsviz/__init__.py
gsheetsviz/connector.py
gsheetsviz/exceptions.py
gsheets_viz-0.2.3.dist-info/LICENSE.txt
gsheets_viz-0.2.3.dist-info/METADATA
gsheets_viz-0.2.3.dist-info/WHEEL
gsheets_viz-0.2.3.dist-info/top_level.txt
gsheets_viz-0.2.3.dist-info/RECORD
